{
    "/js/app.js": "/js/app.js?id=ddae2ca32bb4be7fb619",
    "/js/customizer.js": "/js/customizer.js?id=d574d7bcc53150749506",
    "/js/manifest.js": "/js/manifest.js?id=c9a8a5d9f8ca71793b1e",
    "/css/editor-blocks.css": "/css/editor-blocks.css?id=429c2da0d96ee3186574",
    "/css/editor-styles.css": "/css/editor-styles.css?id=1b1cd70a109fe0d5a7b5",
    "/css/adminbar.css": "/css/adminbar.css?id=9f2b1cd3d2cddbee4c0e",
    "/css/admin.css": "/css/admin.css?id=d00c1cb74269998c7802",
    "/css/style.css": "/css/style.css?id=e5715134e79f1d835d11",
    "/js/vendor.js": "/js/vendor.js?id=a7fecbff060369f2dbce",
    "/images/android-chrome-192x192.png": "/images/android-chrome-192x192.png?id=d4205436f35097ce7ef3",
    "/images/android-chrome-512x512.png": "/images/android-chrome-512x512.png?id=5d0dc81b5f979df5ef44",
    "/images/apple-touch-icon.png": "/images/apple-touch-icon.png?id=cd109d0ec9fc472c6242",
    "/images/avatar.png": "/images/avatar.png?id=2f63f371401cd6f8a88f",
    "/images/favicon-16x16.png": "/images/favicon-16x16.png?id=df3d72d0e622e1e41262",
    "/images/favicon-32x32.png": "/images/favicon-32x32.png?id=48893f3d35825c5717a5",
    "/images/favicon.ico": "/images/favicon.ico?id=6d14a52f6e5f1e81ce28",
    "/images/image-semestre-aula.png": "/images/image-semestre-aula.png?id=db552ed86a2a21fae4b4",
    "/images/line_h.gif": "/images/line_h.gif?id=edcb5bedda0ef19c6f29",
    "/images/line_v.gif": "/images/line_v.gif?id=49588b427df88cf6550c",
    "/images/logo-uoc-default.png": "/images/logo-uoc-default.png?id=4b311e9470712fb21407",
    "/fonts/UOC-Serif.woff": "/fonts/UOC-Serif.woff?id=52723e9658e9e7e2d165",
    "/fonts/UOC-Serif.woff2": "/fonts/UOC-Serif.woff2?id=100e65132b26fe741b4f",
    "/fonts/UOCSans-Bold.otf": "/fonts/UOCSans-Bold.otf?id=ec9bc9486e9e064b018a",
    "/fonts/UOCSans-Bold.svg": "/fonts/UOCSans-Bold.svg?id=818ca8c9891674d48cd0",
    "/fonts/UOCSans-Bold.ttf": "/fonts/UOCSans-Bold.ttf?id=ceef5ff5ec1d7ca85233",
    "/fonts/UOCSans-Bold.woff": "/fonts/UOCSans-Bold.woff?id=2fc936da1c1543fee599",
    "/fonts/UOCSans-Bold.woff2": "/fonts/UOCSans-Bold.woff2?id=7b9748370bc458457252",
    "/fonts/UOCSans-BoldItalic.otf": "/fonts/UOCSans-BoldItalic.otf?id=27723b6d04314f20505e",
    "/fonts/UOCSans-BoldItalic.svg": "/fonts/UOCSans-BoldItalic.svg?id=2babed3dee4f9c299cad",
    "/fonts/UOCSans-BoldItalic.ttf": "/fonts/UOCSans-BoldItalic.ttf?id=1be5dd05084d43cf9e2c",
    "/fonts/UOCSans-BoldItalic.woff": "/fonts/UOCSans-BoldItalic.woff?id=f0bdc6ebef74e4785295",
    "/fonts/UOCSans-BoldItalic.woff2": "/fonts/UOCSans-BoldItalic.woff2?id=5b09ab05414a68d8dc6c",
    "/fonts/UOCSans-Italic.otf": "/fonts/UOCSans-Italic.otf?id=042bad6bd42c421cdc9a",
    "/fonts/UOCSans-Italic.svg": "/fonts/UOCSans-Italic.svg?id=8d66abe426fee43b884d",
    "/fonts/UOCSans-Italic.ttf": "/fonts/UOCSans-Italic.ttf?id=9c12689f0f9a0b984616",
    "/fonts/UOCSans-Italic.woff": "/fonts/UOCSans-Italic.woff?id=05ea610bcfa854a51fe4",
    "/fonts/UOCSans-Italic.woff2": "/fonts/UOCSans-Italic.woff2?id=64d8953be5f4385fc1c0",
    "/fonts/UOCSans-Regular.otf": "/fonts/UOCSans-Regular.otf?id=74a858deebd23f2b23ec",
    "/fonts/UOCSans-Regular.svg": "/fonts/UOCSans-Regular.svg?id=817026e3004c26402b86",
    "/fonts/UOCSans-Regular.ttf": "/fonts/UOCSans-Regular.ttf?id=e533e43bb4455e073018",
    "/fonts/UOCSans-Regular.woff": "/fonts/UOCSans-Regular.woff?id=5ab0dffcf912107bc9bc",
    "/fonts/UOCSans-Regular.woff2": "/fonts/UOCSans-Regular.woff2?id=ad7d5d2d8b1254e97c76",
    "/fonts/UOCSerif-Bold.otf": "/fonts/UOCSerif-Bold.otf?id=f9853a0b1910afe07451",
    "/fonts/UOCSerif-Bold.svg": "/fonts/UOCSerif-Bold.svg?id=4173a1bf00c721875168",
    "/fonts/UOCSerif-Bold.ttf": "/fonts/UOCSerif-Bold.ttf?id=dc057f4ea65e50566d4a",
    "/fonts/UOCSerif-Bold.woff": "/fonts/UOCSerif-Bold.woff?id=e9f7855bf56933b52221",
    "/fonts/UOCSerif-Bold.woff2": "/fonts/UOCSerif-Bold.woff2?id=5b475cf5a0a9fe1dd72d",
    "/fonts/UOCSerif-BoldItalic.otf": "/fonts/UOCSerif-BoldItalic.otf?id=6b979ddb0e74ffb4f6b5",
    "/fonts/UOCSerif-BoldItalic.svg": "/fonts/UOCSerif-BoldItalic.svg?id=a434add29727a0dd4e96",
    "/fonts/UOCSerif-BoldItalic.ttf": "/fonts/UOCSerif-BoldItalic.ttf?id=48f44c065f2357025c61",
    "/fonts/UOCSerif-BoldItalic.woff": "/fonts/UOCSerif-BoldItalic.woff?id=0fee50daa8847ff06086",
    "/fonts/UOCSerif-BoldItalic.woff2": "/fonts/UOCSerif-BoldItalic.woff2?id=b8d58c352daac217c0ae",
    "/fonts/UOCSerif-Italic.otf": "/fonts/UOCSerif-Italic.otf?id=ef2d1a39cbf5a77a245e",
    "/fonts/UOCSerif-Italic.svg": "/fonts/UOCSerif-Italic.svg?id=ea90ab73b34e02049307",
    "/fonts/UOCSerif-Italic.ttf": "/fonts/UOCSerif-Italic.ttf?id=88b8ef2f60b44b7af887",
    "/fonts/UOCSerif-Italic.woff": "/fonts/UOCSerif-Italic.woff?id=d4f2635fbcdc7bda4b2f",
    "/fonts/UOCSerif-Italic.woff2": "/fonts/UOCSerif-Italic.woff2?id=49e925a5bf29e3ecc2b6",
    "/fonts/UOCSerif-Regular.otf": "/fonts/UOCSerif-Regular.otf?id=1bf66f9e34d509d40515",
    "/fonts/UOCSerif-Regular.svg": "/fonts/UOCSerif-Regular.svg?id=c4050d3330093ee0efc6",
    "/fonts/UOCSerif-Regular.ttf": "/fonts/UOCSerif-Regular.ttf?id=198f13bccd25c98304b0",
    "/fonts/UOCSerif-Regular.woff": "/fonts/UOCSerif-Regular.woff?id=db3065e550d20bf599eb",
    "/fonts/UOCSerif-Regular.woff2": "/fonts/UOCSerif-Regular.woff2?id=c971bf6ff5382b36a217",
    "/fonts/fontello.eot": "/fonts/fontello.eot?id=a3e514fcc9640a2eb01a",
    "/fonts/fontello.svg": "/fonts/fontello.svg?id=35501fd9a24f78b38fa0",
    "/fonts/fontello.ttf": "/fonts/fontello.ttf?id=2bd9661cc4c1b16cb8b9",
    "/fonts/fontello.woff": "/fonts/fontello.woff?id=8269bc4531cadbd97b73",
    "/fonts/fontello.woff2": "/fonts/fontello.woff2?id=855ae1e63c1c31af73e9",
    "/iconfonts/icons.ttf": "/iconfonts/icons.ttf?id=562c2897cd3449674930",
    "/iconfonts/icons.woff": "/iconfonts/icons.woff?id=af798383895e9eb7e707",
    "/iconfonts/icons.woff2": "/iconfonts/icons.woff2?id=447b2c70ff392abf7051"
}
